bct/__init__.py
bct-0.0.1.dist-info/LICENSE
bct-0.0.1.dist-info/METADATA
bct-0.0.1.dist-info/WHEEL
bct-0.0.1.dist-info/top_level.txt
bct-0.0.1.dist-info/RECORD
