Metadata-Version: 2.1
Name: bct
Version: 0.0.1
Summary: BeatifulColorText
Home-page: UNKNOWN
Author: Xin1337 & ZayDev
Author-email: <xin1337dev@protonmail.com>
License: UNKNOWN
Keywords: python,tui,terminal,user,interface,color,animation
Platform: UNKNOWN
Classifier: Development Status :: 1 - Planning
Classifier: Intended Audience :: Developers
Classifier: Programming Language :: Python :: 3
Classifier: Operating System :: Unix
Classifier: Operating System :: MacOS :: MacOS X
Classifier: Operating System :: Microsoft :: Windows
Requires-Dist: colored
